[
	{
		"constant": true,
		"inputs": [
			{
				"name": "",
				"type": "uint256"
			}
		],
		"name": "messages",
		"outputs": [
			{
				"name": "owner",
				"type": "address"
			},
			{
				"name": "message",
				"type": "string"
			},
			{
				"name": "created",
				"type": "uint256"
			}
		],
		"payable": false,
		"stateMutability": "view",
		"type": "function"
	},
	{
		"constant": false,
		"inputs": [
			{
				"name": "_message",
				"type": "string"
			}
		],
		"name": "postMessage",
		"outputs": [],
		"payable": false,
		"stateMutability": "nonpayable",
		"type": "function"
	},
	{
		"constant": true,
		"inputs": [],
		"name": "messagesCount",
		"outputs": [
			{
				"name": "",
				"type": "uint256"
			}
		],
		"payable": false,
		"stateMutability": "view",
		"type": "function"
	},
	{
		"anonymous": false,
		"inputs": [
			{
				"indexed": false,
				"name": "id",
				"type": "uint256"
			}
		],
		"name": "NewMessage",
		"type": "event"
	}
]